fli/__init__.py
fli/api/__init__.py
fli/api/airport_search.py
fli/api/kiwi_flights.py
fli/api/kiwi_oneway.py
fli/api/kiwi_roundtrip.py
fli/cli/__init__.py
fli/cli/commands/__init__.py
fli/cli/commands/airport_search.py
fli/cli/commands/cheap.py
fli/cli/commands/search.py
fli/cli/console.py
fli/cli/enums.py
fli/cli/main.py
fli/cli/utils.py
fli/data/translations/airlines_cn.json
fli/data/translations/airports_enhanced_cn.json
fli/models/__init__.py
fli/models/airline.py
fli/models/airport.py
fli/models/google_flights/__init__.py
fli/models/google_flights/base.py
fli/models/google_flights/dates.py
fli/models/google_flights/flights.py
fli/search/__init__.py
fli/search/client.py
fli/search/dates.py
fli/search/flights.py
smart_flights-7.0.1.dist-info/entry_points.txt
smart_flights-7.0.1.dist-info/LICENSE.txt
smart_flights-7.0.1.dist-info/METADATA
smart_flights-7.0.1.dist-info/WHEEL
smart_flights-7.0.1.dist-info/RECORD
