Metadata-Version: 2.3
Name: smart-flights
Version: 7.0.1
Summary: Smart Python library for Google Flights API with bilingual support, intelligent search features, enhanced pagination, and hidden city flights via Kiwi.com API
Keywords: smart-flights,flights,google-flights,travel,api,flight-search,bilingual,intelligent-search,hidden-city,kiwi,cheap-flights
Author: Punit Arani
Author-email: punit@joinslash.com
Requires-Python: >=3.12,<4.0
Classifier: Programming Language :: Python :: 3
Classifier: Programming Language :: Python :: 3.12
Classifier: Programming Language :: Python :: 3.13
Requires-Dist: curl-cffi (>=0.7.4,<0.8.0)
Requires-Dist: httpx (>=0.28.1,<0.29.0)
Requires-Dist: pandas (>=2.2.3,<3.0.0)
Requires-Dist: pydantic (>=2.10.4,<3.0.0)
Requires-Dist: python-dotenv (>=1.0.1,<2.0.0)
Requires-Dist: ratelimit (>=2.2.1,<3.0.0)
Requires-Dist: tenacity (>=9.0.0,<10.0.0)
Requires-Dist: typer (>=0.15.1,<0.16.0)
Project-URL: Documentation, https://punitarani.github.io/fli
Project-URL: Homepage, https://github.com/punitarani/fli
Project-URL: Repository, https://github.com/punitarani/fli
